auth/VERSION
auth/__init__.py
auth/blueprint.py
auth/controllers.py
auth/credentials.py
auth/extensions.py
auth/lib.py
auth/models.py
auth/permissions.py
sample_extension/__init__.py
sample_permission_provider/__init__.py
dhq_auth-0.1.6.dist-info/LICENSE
dhq_auth-0.1.6.dist-info/METADATA
dhq_auth-0.1.6.dist-info/WHEEL
dhq_auth-0.1.6.dist-info/top_level.txt
dhq_auth-0.1.6.dist-info/RECORD
