Metadata-Version: 2.1
Name: dhq-auth
Version: 0.1.6
Summary: {{ DESCRIPTION }}
Home-page: https://github.com/datahq/auth
Author: Adam Kariv, Open Knowledge (International), Datopian
License: MIT
Keywords: data,auth
Platform: UNKNOWN
Classifier: Development Status :: 4 - Beta
Classifier: Environment :: Web Environment
Classifier: Intended Audience :: Developers
Classifier: License :: OSI Approved :: MIT License
Classifier: Operating System :: OS Independent
Classifier: Programming Language :: Python :: 3.6
Classifier: Topic :: Internet :: WWW/HTTP :: Dynamic Content
Classifier: Topic :: Software Development :: Libraries :: Python Modules
Requires-Dist: flask
Requires-Dist: flask-cors
Requires-Dist: flask-jsonpify
Requires-Dist: flask-session
Requires-Dist: flask-oauthlib
Requires-Dist: pyjwt
Requires-Dist: sqlalchemy
Requires-Dist: cryptography
Requires-Dist: psycopg2
Requires-Dist: requests
Provides-Extra: develop
Requires-Dist: pylama ; extra == 'develop'
Requires-Dist: tox ; extra == 'develop'
Requires-Dist: coverage ; extra == 'develop'
Requires-Dist: coveralls ; extra == 'develop'
Requires-Dist: pytest ; extra == 'develop'
Requires-Dist: pytest-cov ; extra == 'develop'
Requires-Dist: requests-mock (==1.3.0) ; extra == 'develop'
